{
  "metadata": {
    "historic": [],
    "timestamp": "1707801945713"
  },

  "author": {
    "name": "Ben",
    "address": "0x15d34AAf54267DB7D7c367839AAf71A00a2C6A65"
  },

  "retweet": null,
  "title": "Sed vel orci id tellus sagittis",
  "content": "Sed vel orci id tellus sagittis venenatis at malesuada ante. Donec dignissim commodo laoreet. Donec finibus velit vel nisl rutrum tristique. Sed mollis bibendum felis sit amet eleifend. Donec cursus libero egestas nisl pulvinar, at tincidunt nisi egestas. Etiam sed fermentum orci. Praesent dictum lorem massa, ac venenatis magna lobortis et. In ut mauris ipsum. Proin eget mauris in augue bibendum congue non a arcu. Praesent egestas risus metus, ac commodo felis laoreet a. Nullam at ante pharetra, ullamcorper eros quis, tincidunt urna."
}